turnstile/__init__.py
turnstile/commit_msg.py
turnstile/manager.py
turnstile/pre_commit.py
turnstile/version.py
turnstile/checks/__init__.py
turnstile/checks/commit_msg/__init__.py
turnstile/checks/commit_msg/branch_pattern.py
turnstile/checks/commit_msg/branch_release.py
turnstile/checks/commit_msg/branch_type.py
turnstile/checks/commit_msg/protect_master.py
turnstile/checks/commit_msg/specification.py
turnstile/common/__init__.py
turnstile/common/config.py
turnstile/common/git.py
turnstile/common/github.py
turnstile/common/output.py
turnstile/manager_subcommands/__init__.py
turnstile/manager_subcommands/config.py
turnstile/manager_subcommands/install.py
turnstile/manager_subcommands/open_spec.py
turnstile/manager_subcommands/remove.py
turnstile/manager_subcommands/specification.py
turnstile/manager_subcommands/upgrade.py
turnstile/manager_subcommands/version.py
turnstile/models/__init__.py
turnstile/models/message.py
turnstile/models/specifications.py
turnstile/models/staging.py
turnstile/toolbox/__init__.py
turnstile_core-2.2.1.dist-info/DESCRIPTION.rst
turnstile_core-2.2.1.dist-info/METADATA
turnstile_core-2.2.1.dist-info/RECORD
turnstile_core-2.2.1.dist-info/WHEEL
turnstile_core-2.2.1.dist-info/entry_points.txt
turnstile_core-2.2.1.dist-info/metadata.json
turnstile_core-2.2.1.dist-info/top_level.txt
