Metadata-Version: 2.0
Name: turnstile-core
Version: 2.2.1
Summary: Turnstile - Local Git Hooks
Home-page: https://github.com/jmcs/turnstile
Author: João Santos
Author-email: UNKNOWN
License: Apache License Version 2.0
Platform: UNKNOWN
Classifier: Programming Language :: Python
Classifier: Programming Language :: Python :: 2.7
Classifier: Programming Language :: Python :: 3.4
Classifier: Development Status :: 4 - Beta
Classifier: Intended Audience :: Developers
Classifier: Operating System :: OS Independent
Classifier: Topic :: Software Development :: Version Control
Requires-Dist: GitPython
Requires-Dist: MapGitConfig
Requires-Dist: PyYAML
Requires-Dist: click
Requires-Dist: pathlib
Requires-Dist: pip
Requires-Dist: pyrsistent
Requires-Dist: requests
Requires-Dist: rfc3986
